src/__init__.py
src/app.py
cliks-0.1.1.dist-info/METADATA
cliks-0.1.1.dist-info/WHEEL
cliks-0.1.1.dist-info/entry_points.txt
cliks-0.1.1.dist-info/top_level.txt
cliks-0.1.1.dist-info/RECORD
