Metadata-Version: 2.1
Name: cliks
Version: 0.1.1
Summary: CLI for facilitate and standardize commit message.
Home-page: https://github.com/augustoliks/cliks
Author: Carlos Neto
Author-email: carlos.santos110@fatec.sp.gov.br
License: UNKNOWN
Keywords: cli,git,commit
Platform: UNKNOWN
Requires-Dist: PyInquirer
Requires-Dist: gitpython
